{
  "project_info": {
    "project_number": "38322737281",
    "project_id": "movie-app-147d4",
    "storage_bucket": "movie-app-147d4.appspot.com"
  },
  "client": [
    {
      "client_info": {
        "mobilesdk_app_id": "1:38322737281:android:9c4a72e8daac787b04bd80",
        "android_client_info": {
          "package_name": "com.example.movieapp"
        }
      },
      "oauth_client": [],
      "api_key": [
        {
          "current_key": "AIzaSyDydnwhRDnp3lw0NEfKjmfCLIKrRhz1MEA"
        }
      ],
      "services": {
        "appinvite_service": {
          "other_platform_oauth_client": []
        }
      }
    }
  ],
  "configuration_version": "1"
}